czespressif/__init__.py
czespressif/config.py
czespressif/czespressif.py
czespressif/defaults.py
czespressif/example.py
czespressif/questions.py
czespressif/templates/CHANGELOG.md.j2
czespressif/templates/RELEASE_NOTES.md.j2
czespressif/templates/espressif-logo.svg
czespressif/templates/macros.md.j2
czespressif-1.4.0.dist-info/licenses/LICENSE
tests/conftest.py
tests/test_changelog.py
tests/test_czespressif.py
czespressif-1.4.0.dist-info/METADATA
czespressif-1.4.0.dist-info/WHEEL
czespressif-1.4.0.dist-info/entry_points.txt
czespressif-1.4.0.dist-info/top_level.txt
czespressif-1.4.0.dist-info/RECORD
