Metadata-Version: 2.4
Name: czespressif
Version: 1.4.0
Summary: Commitizen plugin with Espressif code style
Author: Espressif Systems
Author-email: Tomas Sebestik <tomas.sebestik@espressif.com>
License: Apache 2.0
Project-URL: Changelog, https://github.com/espressif/cz-plugin-espressif/blob/master/CHANGELOG.md
Project-URL: Homepage, https://github.com/espressif/cz-plugin-espressif/
Project-URL: Source, https://github.com/espressif/cz-plugin-espressif/
Project-URL: Tracker, https://github.com/espressif/cz-plugin-espressif/issues/
Classifier: Intended Audience :: Developers
Classifier: License :: OSI Approved :: Apache Software License
Classifier: Natural Language :: English
Classifier: Operating System :: MacOS :: MacOS X
Classifier: Operating System :: Microsoft :: Windows
Classifier: Operating System :: POSIX
Classifier: Programming Language :: Python :: 3
Classifier: Programming Language :: Python :: 3.10
Classifier: Programming Language :: Python :: 3.11
Classifier: Programming Language :: Python :: 3.12
Classifier: Programming Language :: Python :: 3.9
Requires-Python: >=3.9
License-File: LICENSE
Requires-Dist: commitizen>=3.29.0
Provides-Extra: dev
Requires-Dist: just-bin>=1.26.0; extra == "dev"
Requires-Dist: pre-commit>=4.0.1; extra == "dev"
Requires-Dist: twine>=5.1.1; extra == "dev"
Provides-Extra: test
Requires-Dist: pytest-cov>=4.1.0; extra == "test"
Requires-Dist: pytest-mock>=3.14.0; extra == "test"
Requires-Dist: pytest-sugar>=1.0.0; extra == "test"
Requires-Dist: pytest>=7.4.0; extra == "test"
Requires-Dist: syrupy<5.0,>=4.7.0; extra == "test"
Dynamic: license-file
